arxiv_mcp/__init__.py
arxiv_mcp-0.1.3.dist-info/METADATA
arxiv_mcp-0.1.3.dist-info/WHEEL
arxiv_mcp-0.1.3.dist-info/entry_points.txt
arxiv_mcp-0.1.3.dist-info/licenses/LICENSE
arxiv_mcp-0.1.3.dist-info/RECORD
