Metadata-Version: 2.4
Name: arxiv-mcp
Version: 0.1.3
Summary: A simple MCP server to fetch the content of ArXiv papers.
License-File: LICENSE
Requires-Python: >=3.10
Requires-Dist: diskcache>=5.6.3
Requires-Dist: markitdown[pdf]>=0.1.2
Requires-Dist: mcp[cli]>=1.9.3
Requires-Dist: requests>=2.32.4
